Workbook

Sheet Dashboard
B2: PATEL ENGINEERING LTD — FINANCIAL ANALYST DASHBOARD
B4: NSE: PATELENG | BSE: 531120 | Sector: Civil Construction (Dams, Tunnels, Roads, Hydro) | Data as of 5 Jul 2026 (consolidated, Rs. Crores unless noted)
B6: Market Cap (Rs Cr) | C6: CMP (Rs) | D6: Stock P/E | E6: Book Value (Rs) | F6: ROCE % (latest) | G6: ROE % (latest)
B8: =Data_Ratios!B11 -> 2504 | C8: =Data_Ratios!B12 -> 25.3 | D8: =Data_Ratios!B13 -> 6.6 | E8: =Data_Ratios!B14 -> 39.6 | F8: =Data_Ratios!B16 -> 0.154 | G8: =Data_Ratios!B17 -> 0.104
B11: Select Financial Year: | D11: Mar 2025
B13: Revenue (Rs Cr) (selected yr) | C13: Net Profit (Rs Cr) (selected yr) | D13: Operating Margin % (selected yr) | E13: EPS (Rs) (selected yr)
B15: =INDEX(Data_PL!$B$5:$M$5,MATCH(Dashboard!$D$11,Data_PL!$B$4:$M$4,0)) -> 5093 | C15: =INDEX(Data_PL!$B$13:$M$13,MATCH(Dashboard!$D$11,Data_PL!$B$4:$M$4,0)) -> 248 | D15: =INDEX(Data_PL!$B$15:$M$15,MATCH(Dashboard!$D$11,Data_PL!$B$4:$M$4,0)) -> 0.1470646 | E15: =INDEX(Data_PL!$B$14:$M$14,MATCH(Dashboard!$D$11,Data_PL!$B$4:$M$4,0)) -> 2.5
B19: TREND ANALYSIS (FY2014 – FY2025 / TTM)
B76: HOW TO USE THIS DASHBOARD
B77: • Use the gold dropdown cell above to switch the Financial Year and instantly update the four KPI cards.
B78: • All charts and KPIs are linked live to the Data_PL, Data_BS, Data_CF, Data_Ratios, Data_Quarterly and Data_Shareholding tabs.
B79: • Blue-font cells on data tabs are hardcoded source inputs (from screener.in filings); black-font cells are formulas — edit inputs to refresh the whole workbook.
B80: • Add new years/quarters by inserting a column on the relevant Data_ tab; charts use structured ranges so update the chart series range if the data set grows.

Sheet Risk_Dashboard
B2: PATEL ENGINEERING LTD — RISK MANAGEMENT DASHBOARD
B4: Credit, leverage, liquidity & concentration risk indicators — data as of 5 Jul 2026 (Rs. Crores unless noted)
B6: Promoter Pledge % | C6: Interest Coverage (TTM) | D6: Debt / EBITDA (TTM) | E6: Net Debt / Equity | F6: Contingent Liabilities (Rs Cr) | G6: Quality/Risk Score (/100)
B8: =Data_Risk!B6 -> 0.8658 | C8: =Data_Risk!B10 -> 1.48 | D8: =Data_Risk!B9 -> 3.94 | E8: =Data_Risk!B8 -> 0.23 | F8: =Data_Risk!B7 -> 2681 | G8: =Data_Risk!B14 -> 45
B11: RISK SCORECARD
B12: Risk Category | D12: Value | E12: Red Flag Threshold | F12: Status
B13: Governance / Ownership | D13: Promoter Pledge % | E13: =Data_Risk!B6 -> 0.8658 | F13: >50% | G13: HIGH
B14: Leverage | D14: Debt / EBITDA (x) | E14: =Data_Risk!B9 -> 3.94 | F14: >3.0x | G14: HIGH
B15: Leverage | D15: Net Debt / Equity (x) | E15: =Data_Risk!B8 -> 0.23 | F15: >0.5x | G15: LOW
B16: Solvency | D16: Interest Coverage (x) | E16: =Data_Risk!B10 -> 1.48 | F16: <2.0x | G16: HIGH
B17: Profitability | D17: ROCE % (half-year FY26) | E17: =Data_Risk!B11 -> 0.1319 | F17: <10% | G17: MEDIUM
B18: Liquidity | D18: Working Capital % of Assets | E18: =Data_Risk!B12 -> 0.8325 | F18: >70% | G18: HIGH
B19: Cash Quality | D19: OCF / EBITDA | E19: =Data_Risk!B13 -> 0.8066 | F19: <60% | G19: LOW
B20: Contingent Exposure | D20: Contingent Liabilities (Rs Cr) | E20: =Data_Risk!B7 -> 2681 | F20: >2000 | G20: HIGH
B21: Overall Rating | D21: MarketsMojo Score (/100) | E21: =Data_Risk!B14 -> 45 | F21: <50 | G21: HIGH
D23: Legend: | E23: HIGH risk | F23: MEDIUM risk | G23: LOW risk
B25: LEVERAGE & SOLVENCY TRENDS (FY2014 – FY2025)
B45: INTEREST RATE STRESS TEST (adjust the gold cell)
B46: Rate shock on borrowings (bps → %): | E46: =Data_Risk!B25 -> 0.01 | F46: ← edit this % on Data_Risk!B25 to test a different shock
B48: Base Net Profit, FY25 (Rs Cr) | E48: =Data_Risk!B34 -> 248
B49: Stressed Net Profit (Rs Cr) | E49: =Data_Risk!B35 -> 226.1905
B50: Net Profit Impact (Rs Cr) | E50: =Data_Risk!B36 -> -21.8095
B51: Net Profit Impact (%) | E51: =Data_Risk!B37 -> -0.087941532
B54: KEY RISK COMMENTARY
B55: • Governance risk: promoter pledge is very high (86.6%) — in a falling market, lenders enforcing margin calls on pledged shares can accelerate price declines.
B56: • Solvency risk: interest coverage sits below the conventional 2.0x safety threshold, meaning a large share of operating profit is consumed by interest payments, leaving little margin for a downturn.
B57: • Leverage: Debt/EBITDA of ~3.9x is elevated for a cyclical construction business, though Debt/Equity has been trending down as the company deleverages (see Data_BS borrowings trend).
B58: • Liquidity: a very high share of assets is tied up in working capital, typical of EPC/construction contractors but a risk if receivables from government clients are delayed.
B59: • Contingent liabilities of ~Rs 2,681 Cr (mostly guarantees/claims typical of large EPC contractors) represent an off-balance-sheet exposure worth monitoring in the notes to accounts.
B60: • Use the stress test panel above to gauge Net Profit sensitivity to a rise in borrowing costs — useful for scenario planning in a rising-rate environment.

Sheet Data_PL
A1: Patel Engineering Ltd — Profit & Loss (Consolidated, Rs. Crores)
A2: Source: screener.in (BSE/NSE filings) — retrieved 5 Jul 2026
A4: Metric | B4: Mar 2014 | C4: Mar 2015 | D4: Mar 2016 | E4: Mar 2017 | F4: Mar 2018 | G4: Mar 2019 | H4: Mar 2020 | I4: Mar 2021 | J4: Mar 2022 | K4: Mar 2023 | L4: Mar 2024 | M4: Mar 2025 | N4: TTM
A5: Sales | B5: 3701 | C5: 3415 | D5: 4041 | E5: 3884 | F5: 2275 | G5: 2362 | H5: 2617 | I5: 1995 | J5: 3380 | K5: 3891 | L5: 4544 | M5: 5093 | N5: 5293
A6: Expenses | B6: 3234 | C6: 2919 | D6: 3642 | E6: 3463 | F6: 1743 | G6: 1985 | H6: 2432 | I6: 1750 | J6: 2850 | K6: 3330 | L6: 3854 | M6: 4345 | N6: 4606
A7: Operating Profit | B7: 467 | C7: 496 | D7: 399 | E7: 421 | F7: 531 | G7: 377 | H7: 185 | I7: 244 | J7: 530 | K7: 562 | L7: 690 | M7: 749 | N7: 687
A8: Other Income | B8: 99 | C8: 131 | D8: 41 | E8: 165 | F8: 106 | G8: 247 | H8: 202 | I8: -115 | J8: 83 | K8: 149 | L8: 163 | M8: -1 | N8: -5
A9: Interest | B9: 438 | C9: 516 | D9: 602 | E9: 579 | F9: 489 | G9: 370 | H9: 266 | I9: 401 | J9: 420 | K9: 412 | L9: 362 | M9: 322 | N9: 296
A10: Depreciation | B10: 82 | C10: 80 | D10: 55 | E10: 78 | F10: 54 | G10: 50 | H10: 66 | I10: 72 | J10: 82 | K10: 81 | L10: 98 | M10: 100 | N10: 104
A11: Profit Before Tax | B11: 46 | C11: 32 | D11: -216 | E11: -71 | F11: 94 | G11: 204 | H11: 55 | I11: -344 | J11: 112 | K11: 218 | L11: 393 | M11: 326 | N11: 283
A12: Tax % | B12: 0.46 | C12: 0.69 | D12: -0.09 | E12: 0.45 | F12: -0.12 | G12: 0.22 | H12: 0.43 | I12: -0.21 | J12: 0.39 | K12: 0.18 | L12: 0.26 | M12: 0.27
A13: Net Profit | B13: 25 | C13: 10 | D13: -196 | E13: -103 | F13: 105 | G13: 154 | H13: 11 | I13: -291 | J13: 72 | K13: 183 | L13: 290 | M13: 248 | N13: 264
A14: EPS (Rs) | B14: 0.51 | C14: 0.26 | D14: -6.04 | E14: -1.55 | F14: 1.58 | G14: 2.22 | H14: 0.15 | I14: -3.54 | J14: 0.85 | K14: 2.02 | L14: 3.19 | M14: 2.5 | N14: 2.57
A15: OPM % | B15: =B7/B5 -> 0.12618211 | C15: =C7/C5 -> 0.14524158 | D15: =D7/D5 -> 0.098737936 | E15: =E7/E5 -> 0.10839341 | F15: =F7/F5 -> 0.23340659 | G15: =G7/G5 -> 0.1596105 | H15: =H7/H5 -> 0.070691632 | I15: =I7/I5 -> 0.12230576 | ... N15: =N7/N5 -> 0.12979407
A16: Net Profit Margin % | B16: =B13/B5 -> 0.0067549311 | C16: =C13/C5 -> 0.0029282577 | D16: =D13/D5 -> -0.048502846 | E16: =E13/E5 -> -0.026519053 | F16: =F13/F5 -> 0.046153846 | G16: =G13/G5 -> 0.065198984 | H16: =H13/H5 -> 0.0042032862 | I16: =I13/I5 -> -0.14586466 | ... N16: =N13/N5 -> 0.049877196

Sheet Data_BS
A1: Patel Engineering Ltd — Balance Sheet (Consolidated, Rs. Crores)
A2: Source: screener.in (BSE/NSE filings) — retrieved 5 Jul 2026
A4: Metric | B4: Mar 2014 | C4: Mar 2015 | D4: Mar 2016 | E4: Mar 2017 | F4: Mar 2018 | G4: Mar 2019 | H4: Mar 2020 | I4: Mar 2021 | J4: Mar 2022 | K4: Mar 2023 | L4: Mar 2024 | M4: Mar 2025 | N4: Sep 2025
A5: Equity Capital | B5: 8 | C5: 8 | D5: 8 | E5: 16 | F5: 16 | G5: 16 | H5: 41 | I5: 47 | J5: 48 | K5: 77 | L5: 77 | M5: 84 | N5: 84
A6: Reserves | B6: 1785 | C6: 1885 | D6: 1705 | E6: 2123 | F6: 2144 | G6: 2260 | H6: 2506 | I6: 2273 | J6: 2336 | K6: 2811 | L6: 3076 | M6: 3700 | N6: 3849
A7: Borrowings | B7: 4478 | C7: 5163 | D7: 5395 | E7: 4982 | F7: 2910 | G7: 2698 | H7: 2296 | I7: 2296 | J7: 2292 | K7: 1758 | L7: 1910 | M7: 1615 | N7: 1560
A8: Other Liabilities | B8: 2337 | C8: 2183 | D8: 2404 | E8: 2555 | F8: 2344 | G8: 3226 | H8: 3485 | I8: 3471 | J8: 3835 | K8: 4111 | L8: 3933 | M8: 4180 | N8: 4126
A9: Total Liabilities | B9: =SUM(B5:B8) -> 8608 | C9: =SUM(C5:C8) -> 9239 | D9: =SUM(D5:D8) -> 9512 | E9: =SUM(E5:E8) -> 9676 | F9: =SUM(F5:F8) -> 7414 | G9: =SUM(G5:G8) -> 8200 | H9: =SUM(H5:H8) -> 8328 | I9: =SUM(I5:I8) -> 8087 | ... N9: =SUM(N5:N8) -> 9619
A10: Fixed Assets | B10: 674 | C10: 658 | D10: 622 | E10: 629 | F10: 556 | G10: 578 | H10: 607 | I10: 683 | J10: 1181 | K10: 1231 | L10: 1319 | M10: 1328 | N10: 1324
A11: Capital WIP | B11: 786 | C11: 982 | D11: 837 | E11: 868 | F11: 792 | G11: 1063 | H11: 1141 | I11: 679 | J11: 283 | K11: 294 | L11: 233 | M11: 171 | N11: 168
A12: Investments | B12: 134 | C12: 182 | D12: 164 | E12: 138 | F12: 140 | G12: 116 | H12: 79 | I12: 68 | J12: 82 | K12: 135 | L12: 155 | M12: 181 | N12: 118
A13: Other Assets | B13: 7014 | C13: 7417 | D13: 7889 | E13: 8040 | F13: 5926 | G13: 6443 | H13: 6501 | I13: 6658 | J13: 6965 | K13: 7096 | L13: 7289 | M13: 7900 | N13: 8009
A14: Total Assets | B14: =SUM(B10:B13) -> 8608 | C14: =SUM(C10:C13) -> 9239 | D14: =SUM(D10:D13) -> 9512 | E14: =SUM(E10:E13) -> 9675 | F14: =SUM(F10:F13) -> 7414 | G14: =SUM(G10:G13) -> 8200 | H14: =SUM(H10:H13) -> 8328 | I14: =SUM(I10:I13) -> 8088 | ... N14: =SUM(N10:N13) -> 9619
A16: Debt to Equity (x) | B16: =B7/(B5+B6) -> 2.4974902 | C16: =C7/(C5+C6) -> 2.7274168 | D16: =D7/(D5+D6) -> 3.1494454 | E16: =E7/(E5+E6) -> 2.3291258 | F16: =F7/(F5+F6) -> 1.3472222 | G16: =G7/(G5+G6) -> 1.185413 | H16: =H7/(H5+H6) -> 0.90145269 | I16: =I7/(I5+I6) -> 0.98965517 | ... N16: =N7/(N5+N6) -> 0.39664378

Sheet Data_CF
A1: Patel Engineering Ltd — Cash Flow (Consolidated, Rs. Crores)
A2: Source: screener.in (BSE/NSE filings) — retrieved 5 Jul 2026
A4: Metric | B4: Mar 2014 | C4: Mar 2015 | D4: Mar 2016 | E4: Mar 2017 | F4: Mar 2018 | G4: Mar 2019 | H4: Mar 2020 | I4: Mar 2021 | J4: Mar 2022 | K4: Mar 2023 | L4: Mar 2024 | M4: Mar 2025
A5: Cash from Operating Activity | B5: -362 | C5: -1 | D5: -48 | E5: 567 | F5: 403 | G5: 836 | H5: 407 | I5: 389 | J5: 514 | K5: 702 | L5: 688 | M5: 363
A6: Cash from Investing Activity | B6: -377 | C6: -244 | D6: 272 | E6: -222 | F6: 245 | G6: -327 | H6: -47 | I6: 7 | J6: -121 | K6: -224 | L6: -132 | M6: -15
A7: Cash from Financing Activity | B7: 614 | C7: 229 | D7: -311 | E7: -343 | F7: -578 | G7: -513 | H7: -367 | I7: -311 | J7: -340 | K7: -541 | L7: -429 | M7: -283
A8: Net Cash Flow | B8: -125 | C8: -16 | D8: -86 | E8: 2 | F8: 70 | G8: -4 | H8: -7 | I8: 85 | J8: 54 | K8: -63 | L8: 126 | M8: 66
A9: Free Cash Flow | B9: -697 | C9: -241 | D9: 87 | E9: 459 | F9: 552 | G9: 523 | H9: 361 | I9: 275 | J9: 371 | K9: 534 | L9: 541 | M9: 275

Sheet Data_Ratios
A1: Patel Engineering Ltd — Key Ratios (Consolidated)
A2: Source: screener.in (BSE/NSE filings) — retrieved 5 Jul 2026
A4: Metric | B4: Mar 2014 | C4: Mar 2015 | D4: Mar 2016 | E4: Mar 2017 | F4: Mar 2018 | G4: Mar 2019 | H4: Mar 2020 | I4: Mar 2021 | J4: Mar 2022 | K4: Mar 2023 | L4: Mar 2024 | M4: Mar 2025
A5: Debtor Days | B5: 53 | C5: 61 | D5: 46 | E5: 24 | F5: 39 | G5: 35 | H5: 46 | I5: 79 | J5: 61 | K5: 47 | L5: 44 | M5: 54
A6: Working Capital Days | B6: 77 | C6: 99 | D6: 108 | E6: 81 | F6: 132 | G6: 141 | H6: 121 | I6: 261 | J6: 140 | K6: 140 | L6: 117 | M6: 132
A7: ROCE % | B7: 0.08 | C7: 0.08 | D7: 0.07 | E7: 0.08 | F7: 0.11 | G7: 0.1 | H7: 0.06 | I7: 0.06 | J7: 0.12 | K7: 0.13 | L7: 0.14 | M7: 0.15
A9: Current Snapshot Ratios
A10: Metric | B10: Value
A11: Market Cap (Rs Cr) | B11: 2504
A12: Current Price (Rs) | B12: 25.3
A13: Stock P/E (x) | B13: 6.6
A14: Book Value (Rs) | B14: 39.6
A15: Dividend Yield % | B15: 0
A16: ROCE % (latest) | B16: 0.154
A17: ROE % (latest) | B17: 0.104
A18: Face Value (Rs) | B18: 1

Sheet Data_Quarterly
A1: Patel Engineering Ltd — Quarterly Results (Consolidated, Rs. Crores)
A2: Source: screener.in (BSE/NSE filings) — retrieved 5 Jul 2026
A4: Metric | B4: Dec 2022 | C4: Mar 2023 | D4: Jun 2023 | E4: Sep 2023 | F4: Dec 2023 | G4: Mar 2024 | H4: Jun 2024 | I4: Sep 2024 | J4: Dec 2024 | K4: Mar 2025 | L4: Jun 2025 | M4: Sep 2025 | N4: Dec 2025
A5: Sales | B5: 955 | C5: 1205 | D5: 1119 | E5: 1021 | F5: 1061 | G5: 1343 | H5: 1102 | I5: 1174 | J5: 1206 | K5: 1612 | L5: 1233 | M5: 1208 | N5: 1239
A6: Expenses | B6: 814 | C6: 1036 | D6: 948 | E6: 881 | F6: 919 | G6: 1106 | H6: 933 | I6: 1012 | J6: 1022 | K6: 1394 | L6: 1068 | M6: 1050 | N6: 1095
A7: Operating Profit | B7: 140 | C7: 169 | D7: 171 | E7: 140 | F7: 142 | G7: 238 | H7: 169 | I7: 162 | J7: 184 | K7: 218 | L7: 165 | M7: 159 | N7: 145
A8: Other Income | B8: 26 | C8: 35 | D8: 12 | E8: 24 | F8: 52 | G8: 75 | H8: 25 | I8: 42 | J8: 10 | K8: -62 | L8: 39 | M8: 32 | N8: -14
A9: Interest | B9: 105 | C9: 104 | D9: 88 | E9: 92 | F9: 89 | G9: 93 | H9: 84 | I9: 79 | J9: 80 | K9: 79 | L9: 73 | M9: 76 | N9: 68
A10: Depreciation | B10: 21 | C10: 21 | D10: 22 | E10: 23 | F10: 23 | G10: 29 | H10: 26 | I10: 24 | J10: 24 | K10: 26 | L10: 25 | M10: 26 | N10: 26
A11: Profit Before Tax | B11: 40 | C11: 80 | D11: 72 | E11: 49 | F11: 82 | G11: 190 | H11: 83 | I11: 101 | J11: 89 | K11: 52 | L11: 105 | M11: 89 | N11: 37
A12: Net Profit | B12: 24 | C12: 82 | D12: 43 | E12: 38 | F12: 69 | G12: 140 | H12: 55 | I12: 73 | J12: 82 | K12: 38 | L12: 81 | M12: 73 | N12: 72
A13: EPS (Rs) | B13: 0.27 | C13: 0.9 | D13: 0.43 | E13: 0.41 | F13: 0.76 | G13: 1.38 | H13: 0.54 | I13: 0.74 | J13: 0.8 | K13: 0.36 | L13: 0.78 | M13: 0.72 | N13: 0.71
A14: OPM % | B14: =B7/B5 -> 0.14659686 | C14: =C7/C5 -> 0.14024896 | D14: =D7/D5 -> 0.15281501 | E14: =E7/E5 -> 0.13712047 | F14: =F7/F5 -> 0.133836 | G14: =G7/G5 -> 0.17721519 | H14: =H7/H5 -> 0.15335753 | I14: =I7/I5 -> 0.13798978 | ... N14: =N7/N5 -> 0.11702986

Sheet Data_Shareholding
A1: Patel Engineering Ltd — Shareholding Pattern (%)
A2: Source: screener.in (BSE/NSE filings) — retrieved 5 Jul 2026
A4: Category | B4: Mar 2023 | C4: Jun 2023 | D4: Sep 2023 | E4: Dec 2023 | F4: Mar 2024 | G4: Jun 2024 | H4: Sep 2024 | I4: Dec 2024 | J4: Mar 2025 | K4: Jun 2025 | L4: Sep 2025 | M4: Dec 2025
A5: Promoters | B5: 0.3942 | C5: 0.3942 | D5: 0.3942 | E5: 0.3942 | F5: 0.3942 | G5: 0.3611 | H5: 0.3611 | I5: 0.3611 | J5: 0.3611 | K5: 0.3611 | L5: 0.3611 | M5: 0.3148
A6: FIIs | B6: 0.021 | C6: 0.0238 | D6: 0.0236 | E6: 0.0283 | F6: 0.0337 | G6: 0.0368 | H6: 0.0309 | I6: 0.0474 | J6: 0.0501 | K6: 0.0271 | L6: 0.0253 | M6: 0.0252
A7: DIIs | B7: 0.092 | C7: 0.0925 | D7: 0.0625 | E7: 0.0559 | F7: 0.0448 | G7: 0.0622 | H7: 0.0445 | I7: 0.0451 | J7: 0.047 | K7: 0.0491 | L7: 0.0475 | M7: 0.0581
A8: Public | B8: 0.4449 | C8: 0.4415 | D8: 0.4718 | E8: 0.4737 | F8: 0.4793 | G8: 0.4959 | H8: 0.5196 | I8: 0.5023 | J8: 0.498 | K8: 0.5188 | L8: 0.5221 | M8: 0.5643
A9: Others | B9: 0.0479 | C9: 0.0479 | D9: 0.0479 | E9: 0.0479 | F9: 0.0479 | G9: 0.0439 | H9: 0.0439 | I9: 0.0439 | J9: 0.0439 | K9: 0.0439 | L9: 0.0439 | M9: 0.0374

Sheet Data_Risk
A1: Patel Engineering Ltd — Risk Management Data
A2: Sources: screener.in, moneyworks4me, samco, marketsmojo — retrieved 5 Jul 2026
A4: Point-in-Time Risk Indicators
A5: Metric | B5: Value | C5: Flag Threshold (Red)
A6: Promoter Pledge (% of promoter holding) | B6: 0.8658 | C6: > 50%
A7: Contingent Liabilities (Rs Cr) | B7: 2681 | C7: > 2000
A8: Net Debt / Equity (x) | B8: 0.23 | C8: > 0.5x
A9: Debt / EBITDA (x, TTM) | B9: 3.94 | C9: > 3.0x
A10: Interest Coverage Ratio (x, TTM) | B10: 1.48 | C10: < 2.0x
A11: ROCE % (half-year FY26) | B11: 0.1319 | C11: < 10%
A12: Working Capital as % of Total Assets | B12: 0.8325 | C12: > 70%
A13: Operating Cash Conversion (OCF/EBITDA) | B13: 0.8066 | C13: < 60%
A14: MarketsMojo Quality/Risk Score (out of 100) | B14: 45 | C14: < 50
A16: Note: figures are latest available snapshot values (TTM / most recent quarter); see Dashboard sources for citations.
A18: Interest Coverage & Leverage Trend (FY, computed)
A19: Metric | B19: =Data_PL!B4 -> Mar 2014 | C19: =Data_PL!C4 -> Mar 2015 | D19: =Data_PL!D4 -> Mar 2016 | E19: =Data_PL!E4 -> Mar 2017 | F19: =Data_PL!F4 -> Mar 2018 | G19: =Data_PL!G4 -> Mar 2019 | H19: =Data_PL!H4 -> Mar 2020 | I19: =Data_PL!I4 -> Mar 2021 | ... M19: =Data_PL!M4 -> Mar 2025
A20: Interest Coverage (EBIT/Interest) | B20: =(Data_PL!B11+Data_PL!B9)/Data_PL!B9 -> 1.1050228 | C20: =(Data_PL!C11+Data_PL!C9)/Data_PL!C9 -> 1.0620155 | D20: =(Data_PL!D11+Data_PL!D9)/Data_PL!D9 -> 0.64119601 | E20: =(Data_PL!E11+Data_PL!E9)/Data_PL!E9 -> 0.87737478 | F20: =(Data_PL!F11+Data_PL!F9)/Data_PL!F9 -> 1.192229 | G20: =(Data_PL!G11+Data_PL!G9)/Data_PL!G9 -> 1.5513514 | H20: =(Data_PL!H11+Data_PL!H9)/Data_PL!H9 -> 1.2067669 | I20: =(Data_PL!I11+Data_PL!I9)/Data_PL!I9 -> 0.14214464 | ... M20: =(Data_PL!M11+Data_PL!M9)/Data_PL!M9 -> 2.0124224
A21: Debt / EBITDA (x) | B21: =Data_BS!B7/Data_PL!B7 -> 9.5888651 | C21: =Data_BS!C7/Data_PL!C7 -> 10.409274 | D21: =Data_BS!D7/Data_PL!D7 -> 13.521303 | E21: =Data_BS!E7/Data_PL!E7 -> 11.833729 | F21: =Data_BS!F7/Data_PL!F7 -> 5.480226 | G21: =Data_BS!G7/Data_PL!G7 -> 7.1564987 | H21: =Data_BS!H7/Data_PL!H7 -> 12.410811 | I21: =Data_BS!I7/Data_PL!I7 -> 9.4098361 | ... M21: =Data_BS!M7/Data_PL!M7 -> 2.1562083
A22: Debt / Equity (x) | B22: =Data_BS!B16 -> 2.4974902 | C22: =Data_BS!C16 -> 2.7274168 | D22: =Data_BS!D16 -> 3.1494454 | E22: =Data_BS!E16 -> 2.3291258 | F22: =Data_BS!F16 -> 1.3472222 | G22: =Data_BS!G16 -> 1.185413 | H22: =Data_BS!H16 -> 0.90145269 | I22: =Data_BS!I16 -> 0.98965517 | ... M22: =Data_BS!M16 -> 0.42679704
A24: Interest Rate Stress Test (based on FY25 actuals)
A25: Assumption: Rate shock on borrowings (bps) | B25: 0.01
A27: Base Borrowings, FY25 (Rs Cr) | B27: =Data_BS!$M$7 -> 1615
A28: Additional Interest Cost (Rs Cr) | B28: =Data_BS!$M$7*$B$25 -> 16.15
A29: Base Interest, FY25 (Rs Cr) | B29: =Data_PL!$M$9 -> 322
A30: Stressed Interest (Rs Cr) | B30: =B29+B28 -> 338.15
A31: Base PBT, FY25 (Rs Cr) | B31: =Data_PL!$M$11 -> 326
A32: Stressed PBT (Rs Cr) | B32: =B31-B28 -> 309.85
A33: Effective Tax Rate FY25 | B33: =Data_PL!$M$12 -> 0.27
A34: Base Net Profit, FY25 (Rs Cr) | B34: =Data_PL!$M$13 -> 248
A35: Stressed Net Profit (Rs Cr) | B35: =B32*(1-B33) -> 226.1905
A36: Net Profit Impact (Rs Cr) | B36: =B35-B34 -> -21.8095
A37: Net Profit Impact (%) | B37: =B36/B34 -> -0.087941532
